bmp581.py
circuitpython_bmp581-0.2.0.dist-info/LICENSE
circuitpython_bmp581-0.2.0.dist-info/METADATA
circuitpython_bmp581-0.2.0.dist-info/WHEEL
circuitpython_bmp581-0.2.0.dist-info/top_level.txt
circuitpython_bmp581-0.2.0.dist-info/RECORD
