Metadata-Version: 2.1
Name: circuitpython-bmp581
Version: 0.2.0
Summary: CircuitPython Driver for the Bosch BMP581 pressure sensor
Author-email: JDM <jdm@mozmail.com>
License: MIT
Project-URL: Homepage, https://github.com/jposada202020/CircuitPython_BMP581
Keywords: sensor,blinka,circuitpython,micropython,bmp581,pressure,temperature,bosch,sensor,BMP581
Classifier: Intended Audience :: Developers
Classifier: Topic :: Software Development :: Libraries
Classifier: Topic :: Software Development :: Embedded Systems
Classifier: Topic :: System :: Hardware
Classifier: License :: OSI Approved :: MIT License
Classifier: Programming Language :: Python :: 3
License-File: LICENSE
Requires-Dist: Adafruit-Blinka
Requires-Dist: adafruit-circuitpython-busdevice
Requires-Dist: adafruit-circuitpython-register
Provides-Extra: optional
